mplextensions/__init__.py
mplextensions/plotting_functions.py
mplextensions/utils.py
matplotlib_extensions-0.2.3.dist-info/LICENSE
matplotlib_extensions-0.2.3.dist-info/METADATA
matplotlib_extensions-0.2.3.dist-info/WHEEL
matplotlib_extensions-0.2.3.dist-info/top_level.txt
matplotlib_extensions-0.2.3.dist-info/RECORD
